{
  "timestamp": "2025-11-22 07:50:30",
  "requested_size_min": 60,
  "requested_size_max": 150,
  "total_posts": 571,
  "valid_for_averages": 257,
  "overall_avg_price_per_sqm": 106727626,
  "age_intervals": {
    "0-4": {
      "avg": 110645962,
      "count": 161
    },
    "5-9": {
      "avg": 101098039,
      "count": 51
    },
    "10-14": {
      "avg": 99409090,
      "count": 44
    },
    "15-20": {
      "avg": 85000000,
      "count": 1
    }
  },
  "size_intervals": {
    "<80": {
      "avg": 103320000,
      "count": 100
    },
    "80-120": {
      "avg": 108790322,
      "count": 124
    },
    ">120": {
      "avg": 109303030,
      "count": 33
    }
  },
  "age_size_matrix": {
    "0-4": {
      "<80": {
        "avg": 106897959,
        "count": 49
      },
      "80-120": {
        "avg": 112662650,
        "count": 83
      },
      ">120": {
        "avg": 111206896,
        "count": 29
      }
    },
    "5-9": {
      "<80": {
        "avg": 99047619,
        "count": 21
      },
      "80-120": {
        "avg": 102740740,
        "count": 27
      },
      ">120": {
        "avg": 100666666,
        "count": 3
      }
    },
    "10-14": {
      "<80": {
        "avg": 101000000,
        "count": 29
      },
      "80-120": {
        "avg": 97500000,
        "count": 14
      },
      ">120": {
        "avg": 80000000,
        "count": 1
      }
    },
    "15-20": {
      "<80": {
        "avg": 85000000,
        "count": 1
      },
      "80-120": {
        "avg": 0,
        "count": 0
      },
      ">120": {
        "avg": 0,
        "count": 0
      }
    }
  }
}